reconciler/__init__.py
reconciler/main.py
reconciler/utils.py
reconciler/webutils.py
reconciler-0.2.2.dist-info/LICENSE
reconciler-0.2.2.dist-info/METADATA
reconciler-0.2.2.dist-info/WHEEL
reconciler-0.2.2.dist-info/top_level.txt
reconciler-0.2.2.dist-info/RECORD
