Metadata-Version: 2.1
Name: reconciler
Version: 0.2.2
Summary: Python utility to reconcile Pandas DataFrames
Home-page: https://github.com/jvfe/reconciler
Author: João Vitor F. Cavalcante
Author-email: jvfe@ufrn.edu.br
License: BSD license
Project-URL: Bug Tracker, https://github.com/jvfe/reconciler/issues
Project-URL: Documentation, https://jvfe.github.io/reconciler/
Project-URL: Source Code, https://github.com/jvfe/reconciler
Keywords: tabular wikidata opendata linked-data
Classifier: Development Status :: 3 - Alpha
Classifier: Intended Audience :: Developers
Classifier: Intended Audience :: Information Technology
Classifier: Intended Audience :: Science/Research
Classifier: License :: OSI Approved :: BSD License
Classifier: Natural Language :: English
Classifier: Programming Language :: Python :: 3
Classifier: Programming Language :: Python :: 3.6
Classifier: Programming Language :: Python :: 3.7
Classifier: Programming Language :: Python :: 3.8
Requires-Python: >=3.6
License-File: LICENSE
Requires-Dist: requests
Requires-Dist: pandas
Requires-Dist: tqdm
